<?xml version = '1.0' encoding = 'UTF-8'?>
<Diagram class="oracle.dbtools.crest.swingui.relational.DPVRelational" name="Relational_1" id="A70945E2-92F5-7E1C-478C-9FCEC1CE05F5">
<createdBy>charming</createdBy>
<modifiedBy>charming</modifiedBy>
<createdTime>2023-12-17 10:51:58 UTC</createdTime>
<autoRoute>false</autoRoute>
<boxInbox>true</boxInbox>
<showLegend>false</showLegend>
<showLabels>false</showLabels>
<showRelAttributes>false</showRelAttributes>
<gridEnabled>false</gridEnabled>
<showGrid>false</showGrid>
<diagramColor>-1</diagramColor>
<display>false</display>
<notation>1</notation>
<objectViews>
<OView class="oracle.dbtools.crest.swingui.relational.TVTable" oid="4C18F7C0-540C-6BAB-D18E-E94991B2CD52" otype="Table" vid="F97B13F9-62C8-08D9-C578-15C25E097EA3">
<hideElementsInCurrentOnly>false</hideElementsInCurrentOnly>
<bounds x="11" y="615" width="209" height="92"/>
</OView>
<OView class="oracle.dbtools.crest.swingui.relational.TVTable" oid="646185DD-EF33-D2B4-7C2F-05F49F6CF500" otype="Table" vid="CB09A6DF-04F3-8861-4D73-AEFDBF5D6A2C">
<hideElementsInCurrentOnly>false</hideElementsInCurrentOnly>
<bounds x="27" y="27" width="291" height="179"/>
</OView>
<OView class="oracle.dbtools.crest.swingui.relational.TVTable" oid="6AEC987C-8FFE-7EF5-A8BB-DF5C257F5394" otype="Table" vid="C1B05936-3154-111E-E222-2609C42F42D4">
<hideElementsInCurrentOnly>false</hideElementsInCurrentOnly>
<bounds x="913" y="141" width="278" height="179"/>
</OView>
<OView class="oracle.dbtools.crest.swingui.relational.TVTable" oid="8427F5BC-DEB1-FC8B-B43A-3156348DB1C5" otype="Table" vid="1380A437-7632-214F-DC34-E12F3AB9533C">
<hideElementsInCurrentOnly>false</hideElementsInCurrentOnly>
<bounds x="13" y="283" width="374" height="225"/>
</OView>
<OView class="oracle.dbtools.crest.swingui.relational.TVTable" oid="8AA00550-060F-7B50-E64F-A7099ED5C5D9" otype="Table" vid="6ECD7A4A-4902-910F-B327-06C56C06BC36">
<hideElementsInCurrentOnly>false</hideElementsInCurrentOnly>
<bounds x="262" y="615" width="241" height="96"/>
</OView>
<OView class="oracle.dbtools.crest.swingui.relational.TVTable" oid="C370B8B5-7748-00BB-0569-362CFED1F7AB" otype="Table" vid="DEB93568-555D-B208-D010-C467733AF64D">
<hideElementsInCurrentOnly>false</hideElementsInCurrentOnly>
<bounds x="485" y="280" width="275" height="136"/>
</OView>
<OView class="oracle.dbtools.crest.swingui.relational.TVTable" oid="E9122F47-8877-24D4-FC72-09B442D05DDB" otype="Table" vid="837A602E-2A39-65B5-82DA-16A0EB3903A5">
<hideElementsInCurrentOnly>false</hideElementsInCurrentOnly>
<bounds x="945" y="16" width="226" height="58"/>
</OView>
</objectViews>
<connectors>
<Connector class="oracle.dbtools.crest.swingui.relational.TVFKRelation" oid="210C0A49-9653-5ED9-105D-78D49801A66A" otype="FKIndexAssociation" vid_source="1380A437-7632-214F-DC34-E12F3AB9533C" vid_target="DEB93568-555D-B208-D010-C467733AF64D">
<hideElementsInCurrentOnly>false</hideElementsInCurrentOnly>
<backgroundColor>-16777216</backgroundColor>
<lineWidth>1</lineWidth>
<points>
<point x="387" y="364"/>
<point x="485" y="364"/>
</points>
</Connector>
<Connector class="oracle.dbtools.crest.swingui.relational.TVFKRelation" oid="2E7F62F1-7128-8616-2410-C3FEC3100EB1" otype="FKIndexAssociation" vid_source="837A602E-2A39-65B5-82DA-16A0EB3903A5" vid_target="C1B05936-3154-111E-E222-2609C42F42D4">
<hideElementsInCurrentOnly>false</hideElementsInCurrentOnly>
<backgroundColor>-16777216</backgroundColor>
<lineWidth>1</lineWidth>
<points>
<point x="1028" y="74"/>
<point x="1028" y="141"/>
</points>
</Connector>
<Connector class="oracle.dbtools.crest.swingui.relational.TVFKRelation" oid="4C6F3BB8-5AFB-31A6-22F4-A11E6318E34F" otype="FKIndexAssociation" vid_source="CB09A6DF-04F3-8861-4D73-AEFDBF5D6A2C" vid_target="1380A437-7632-214F-DC34-E12F3AB9533C">
<hideElementsInCurrentOnly>false</hideElementsInCurrentOnly>
<backgroundColor>-16777216</backgroundColor>
<lineWidth>1</lineWidth>
<points>
<point x="187" y="206"/>
<point x="187" y="283"/>
</points>
</Connector>
<Connector class="oracle.dbtools.crest.swingui.relational.TVFKRelation" oid="A4FD2892-97F7-8A0B-DFAD-B86707726AEB" otype="FKIndexAssociation" vid_source="6ECD7A4A-4902-910F-B327-06C56C06BC36" vid_target="1380A437-7632-214F-DC34-E12F3AB9533C">
<hideElementsInCurrentOnly>false</hideElementsInCurrentOnly>
<backgroundColor>-16777216</backgroundColor>
<lineWidth>1</lineWidth>
<points>
<point x="324" y="615"/>
<point x="324" y="508"/>
</points>
</Connector>
<Connector class="oracle.dbtools.crest.swingui.relational.TVFKRelation" oid="C13F15DD-ECE4-8478-FBC2-3E39E5888BBD" otype="FKIndexAssociation" vid_source="F97B13F9-62C8-08D9-C578-15C25E097EA3" vid_target="1380A437-7632-214F-DC34-E12F3AB9533C">
<hideElementsInCurrentOnly>false</hideElementsInCurrentOnly>
<backgroundColor>-16777216</backgroundColor>
<lineWidth>1</lineWidth>
<points>
<point x="116" y="615"/>
<point x="116" y="508"/>
</points>
</Connector>
<Connector class="oracle.dbtools.crest.swingui.relational.TVFKRelation" oid="E0115CA4-6DE9-6C60-4BE1-DF228AE6733B" otype="FKIndexAssociation" vid_source="837A602E-2A39-65B5-82DA-16A0EB3903A5" vid_target="C1B05936-3154-111E-E222-2609C42F42D4">
<hideElementsInCurrentOnly>false</hideElementsInCurrentOnly>
<backgroundColor>-16777216</backgroundColor>
<lineWidth>1</lineWidth>
<points>
<point x="1103" y="74"/>
<point x="1103" y="141"/>
</points>
</Connector>
<Connector class="oracle.dbtools.crest.swingui.relational.TVFKRelation" oid="E3A7A7F5-CF31-B4F3-0C6A-2A763D5695EE" otype="FKIndexAssociation" vid_source="C1B05936-3154-111E-E222-2609C42F42D4" vid_target="DEB93568-555D-B208-D010-C467733AF64D">
<hideElementsInCurrentOnly>false</hideElementsInCurrentOnly>
<backgroundColor>-16777216</backgroundColor>
<lineWidth>1</lineWidth>
<points>
<point x="913" y="285"/>
<point x="760" y="285"/>
</points>
</Connector>
</connectors>
</Diagram>