<?xml version = '1.0' encoding = 'UTF-8'?>
<Relation class="oracle.dbtools.crest.model.design.logical.Relation" name="Relation_4" directorySegmentName="seg_0" id="8DE5FCA4-7D22-BC6B-561B-F108541875A7">
<createdBy>charming</createdBy>
<createdTime>2023-12-17 10:50:08 UTC</createdTime>
<ownerDesignName>logicalDiagram</ownerDesignName>
<engineerTo>
<item key="AB0CA140-CC97-0796-3D24-445B9A621E39" value="true"/>
</engineerTo>
<identifying>false</identifying>
<optionalSource>true</optionalSource>
<optionalTarget>false</optionalTarget>
<sourceCardinality>1</sourceCardinality>
<sourceEntity>CAACE36C-2659-A26C-C1C2-D1DA982BDD0F</sourceEntity>
<targetCardinalityString>*</targetCardinalityString>
<targetEntity>A8E8795A-96E9-979D-2A96-C41E997FBE41</targetEntity>
<transferable>true</transferable>
<deleteRule>NO ACTION</deleteRule>
</Relation>